half&full adders [Day-02]/full_adder.v
module full_adder(a,b,ci,sum,co);
input a,b,ci;
output sum,co;
assign sum = a^b^ci;
assign co= a&b|b&ci|ci&a;
endmodule

half&full adders [Day-02]/full_adder_tb.v
`include "full_adder.v"

module full_adder_tb;
    reg a, b, ci;
    wire sum, co;
    integer i;
    
    full_adder fa1(a, b, ci, sum, co);

    initial begin
        $dumpfile("output.vcd");
        $dumpvars(0, full_adder_tb);
        
        // Initialize input values
        a = 0; b = 0; ci = 0;
    end

    initial begin
        for (i = 0; i < 8; i = i + 1) begin
            {a, b, ci} = i; #10;

        end
        $finish;
    end

    initial begin
        $monitor($time, "sum=%b, co=%b, a=%b, b=%b, ci=%b", sum, co, a, b, ci);
    end
endmodule

half&full adders [Day-02]/full_adder_output.vcd
$date
	Tue Feb 13 22:29:56 2024
$end
$version
	Icarus Verilog
$end
$timescale
	1s
$end
$scope module full_adder_tb $end
$var wire 1 ! sum $end
$var wire 1 " co $end
$var reg 1 # a $end
$var reg 1 $ b $end
$var reg 1 % ci $end
$var integer 32 & i [31:0] $end
$scope module fa1 $end
$var wire 1 # a $end
$var wire 1 $ b $end
$var wire 1 % ci $end
$var wire 1 " co $end
$var wire 1 ! sum $end
$upscope $end
$upscope $end
$enddefinitions $end
#0
$dumpvars
b0 &
0%
0$
0#
0"
0!
$end
#10
1!
1%
b1 &
#20
1!
1$
0%
b10 &
#30
1"
0!
1%
b11 &
#40
0"
1!
1#
0$
0%
b100 &
#50
1"
0!
1%
b101 &
#60
1"
0!
1$
0%
b110 &
#70
1!
1%
b111 &
#80
b1000 &
